markdeck/__init__.py
markdeck/__main__.py
markdeck/cli.py
markdeck/parser.py
markdeck/server.py
markdeck/watcher.py
markdeck/static/beige.css
markdeck/static/dark.css
markdeck/static/index.html
markdeck/static/light.css
markdeck/static/slides.js
markdeck/static/style.css
markdeck-0.6.0.dist-info/METADATA
markdeck-0.6.0.dist-info/WHEEL
markdeck-0.6.0.dist-info/entry_points.txt
markdeck-0.6.0.dist-info/licenses/LICENSE
markdeck-0.6.0.dist-info/RECORD
