Metadata-Version: 2.4
Name: markdeck
Version: 0.6.0
Summary: A lightweight markdown presentation tool
Author: Orangewise
License: MIT
License-File: LICENSE
Keywords: cli,markdown,presentation,slides
Classifier: Development Status :: 3 - Alpha
Classifier: Intended Audience :: Developers
Classifier: License :: OSI Approved :: MIT License
Classifier: Programming Language :: Python :: 3
Classifier: Programming Language :: Python :: 3.11
Classifier: Programming Language :: Python :: 3.12
Requires-Python: >=3.11
Requires-Dist: click>=8.1.0
Requires-Dist: fastapi>=0.104.0
Requires-Dist: markdown>=3.5.0
Requires-Dist: uvicorn[standard]>=0.24.0
Requires-Dist: watchfiles>=0.21.0
Provides-Extra: dev
Requires-Dist: build>=1.0.0; extra == 'dev'
Requires-Dist: httpx>=0.25.0; extra == 'dev'
Requires-Dist: pytest-asyncio>=0.21.0; extra == 'dev'
Requires-Dist: pytest>=7.4.0; extra == 'dev'
Requires-Dist: ruff>=0.1.0; extra == 'dev'
Requires-Dist: twine>=4.0.0; extra == 'dev'
Provides-Extra: screenshots
Requires-Dist: pillow>=10.0.0; extra == 'screenshots'
Requires-Dist: pixelmatch>=0.3.0; extra == 'screenshots'
Requires-Dist: playwright>=1.40.0; extra == 'screenshots'
